h5py_like/__init__.py
h5py_like/attributes.py
h5py_like/base.py
h5py_like/common.py
h5py_like/dataset.py
h5py_like/file.py
h5py_like/group.py
h5py_like/shape_utils.py
h5py_like/version.py
h5py_like/test_utils/__init__.py
h5py_like/test_utils/common.py
h5py_like/test_utils/dataset.py
h5py_like/test_utils/file.py
h5py_like/test_utils/group.py
h5py_like-0.6.0.dist-info/LICENSE
h5py_like-0.6.0.dist-info/METADATA
h5py_like-0.6.0.dist-info/WHEEL
h5py_like-0.6.0.dist-info/top_level.txt
h5py_like-0.6.0.dist-info/RECORD
