Metadata-Version: 2.1
Name: h5py-like
Version: 0.6.0
Summary: Abstract base classes for making h5py-like objects.
Home-page: https://github.com/barnesc/h5py_like
Author: Chris Lloyd Barnes
Author-email: barnesc@janelia.hhmi.org
License: MIT license
Keywords: h5py
Platform: UNKNOWN
Classifier: Development Status :: 2 - Pre-Alpha
Classifier: Intended Audience :: Developers
Classifier: License :: OSI Approved :: MIT License
Classifier: Natural Language :: English
Classifier: Programming Language :: Python :: 3.7
Requires-Dist: numpy
Provides-Extra: test
Requires-Dist: pytest (>=4.6.3) ; extra == 'test'
